[
  {
    "id": 1,
    "products": [
      {
        "product": "3",
        "quantity": 1
      },
      {
        "product": "2",
        "quantity": 1
      },
      {
        "product": "1",
        "quantity": 1
      },
      {
        "product": "4",
        "quantity": 1
      },
      {
        "product": "2",
        "quantity": 1
      },
      {
        "product": "2",
        "quantity": 1
      },
      {
        "id": 3,
        "quantity": 1
      },
      {
        "id": 98,
        "quantity": 3
      },
      {
        "id": "1414",
        "quantity": 1
      },
      {
        "id": "8",
        "quantity": 1
      },
      {
        "id": 6786,
        "quantity": 1
      }
    ]
  },
  {
    "id": 2,
    "products": [
      {
        "id": 78,
        "quantity": 1
      },
      {
        "id": 748,
        "quantity": 1
      },
      {
        "id": 7,
        "quantity": 1
      },
      {
        "id": 888888,
        "quantity": 1
      },
      {
        "id": 999,
        "quantity": 1
      }
    ]
  },
  {
    "id": 3,
    "products": []
  },
  {
    "id": 4,
    "products": []
  },
  {
    "id": 5,
    "products": [
      {
        "id": 7878,
        "quantity": 2
      },
      {
        "id": 7824,
        "quantity": 1
      }
    ]
  }
]